mem_cli/__init__.py
mem_cli/__main__.py
mem_cli/commands/__init__.py
mem_cli/interface/__init__.py
mem_cli/interface/doc_group.py
mem_cli/interface/navigator_search.py
mem_cli/interface/style.css
mem_cli/interface/wizard_dynamic.py
mem_cli-0.1.1.dist-info/METADATA
mem_cli-0.1.1.dist-info/WHEEL
mem_cli-0.1.1.dist-info/entry_points.txt
mem_cli-0.1.1.dist-info/top_level.txt
mem_cli-0.1.1.dist-info/RECORD
