Metadata-Version: 2.4
Name: mem_cli
Version: 0.1.1
Summary: Interface CLI interactive avec Textual et Click
Author-email: Guillaume Lefebvre <guillaume@ldmail.fr>
License-Expression: MIT
Requires-Python: >=3.9
Requires-Dist: click
Requires-Dist: textual
Requires-Dist: rich
